qal/__init__.py
qal/common/__init__.py
qal/common/diff.py
qal/common/discover.py
qal/common/json.py
qal/common/listhelper.py
qal/common/meta.py
qal/common/recurse.py
qal/common/resources.py
qal/common/strings.py
qal/common/xml_utils.py
qal/dal/__init__.py
qal/dal/conversions.py
qal/dal/dal.py
qal/dal/types.py
qal/dataset/__init__.py
qal/dataset/custom.py
qal/dataset/factory.py
qal/dataset/files.py
qal/dataset/flatfile.py
qal/dataset/matrix.py
qal/dataset/rdbms.py
qal/dataset/spreadsheet.py
qal/dataset/xpath.py
qal/sql/__init__.py
qal/sql/base.py
qal/sql/json.py
qal/sql/macros.py
qal/sql/meta_queries.py
qal/sql/remotable.py
qal/sql/sql.py
qal/sql/types.py
qal/sql/utils.py
qal/tools/__init__.py
qal/tools/optimal_sync.py
qal-0.6.dist-info/DESCRIPTION.rst
qal-0.6.dist-info/METADATA
qal-0.6.dist-info/RECORD
qal-0.6.dist-info/WHEEL
qal-0.6.dist-info/metadata.json
qal-0.6.dist-info/top_level.txt
