Metadata-Version: 2.0
Name: qal
Version: 0.6
Summary: QAL is a Python library for mixing and merging data involving different sources and destinations.
Home-page: https://sourceforge.net/projects/qal/
Author: Nicklas Boerjesson
Author-email: nicklas_attheold_optimalbpm.se
License: BSD
Platform: UNKNOWN
